__int__.py
tools.py
api_code_tools-0.0.2.dist-info/LICENSE
api_code_tools-0.0.2.dist-info/METADATA
api_code_tools-0.0.2.dist-info/WHEEL
api_code_tools-0.0.2.dist-info/top_level.txt
api_code_tools-0.0.2.dist-info/RECORD
