Metadata-Version: 2.1
Name: api-code-tools
Version: 0.0.2
Summary: own tools
Author-email: alhumsi <alhomsidev@gamil.com>
License: MIT License        
Project-URL: Homepage, https://t.me/api_tele
Project-URL: Bug Tracker, https://t.me/alhumsi
Classifier: Programming Language :: Python :: 3
Classifier: License :: OSI Approved :: MIT License
Classifier: Operating System :: OS Independent
Requires-Python: >=3
License-File: LICENSE
